ycnbc/__init__.py
ycnbc/exceptions.py
ycnbc/version.py
ycnbc/markets/__init__.py
ycnbc/markets/markets_base.py
ycnbc/markets/markets_utils.py
ycnbc/news/__init__.py
ycnbc/news/news_base.py
ycnbc/news/news_utils.py
ycnbc/news/uri.py
ycnbc-1.0.11.dist-info/licenses/LICENSE
ycnbc-1.0.11.dist-info/METADATA
ycnbc-1.0.11.dist-info/WHEEL
ycnbc-1.0.11.dist-info/top_level.txt
ycnbc-1.0.11.dist-info/RECORD
