Metadata-Version: 2.4
Name: ycnbc
Version: 1.0.11
Summary: Download data from CNBC!
Home-page: https://github.com/asepscareer/ycnbc
Author: Asep Saputra
Author-email: asepscareer@gmail.com
License: Apache
Keywords: scrape news,cnbc library,cnbc python,cnbc api
Platform: any
Classifier: License :: OSI Approved :: Apache Software License
Classifier: Development Status :: 5 - Production/Stable
Classifier: Operating System :: OS Independent
Classifier: Intended Audience :: Developers
Classifier: Topic :: Internet :: WWW/HTTP :: Dynamic Content :: News/Diary
Classifier: Topic :: Office/Business :: Financial
Classifier: Topic :: Office/Business :: Financial :: Investment
Classifier: Topic :: Scientific/Engineering :: Interface Engine/Protocol Translator
Classifier: Topic :: Software Development :: Libraries
Classifier: Topic :: Software Development :: Libraries :: Python Modules
Classifier: Programming Language :: Python :: 3.8
Classifier: Programming Language :: Python :: 3.9
Classifier: Programming Language :: Python :: 3.10
Classifier: Programming Language :: Python :: 3.11
Classifier: Programming Language :: Python :: 3.12
License-File: LICENSE
Requires-Dist: curl-cffi>=0.5.9
Requires-Dist: lxml>=4.9.3
Requires-Dist: cssselect>=1.2.0
Requires-Dist: mypy
Requires-Dist: tenacity
Dynamic: author
Dynamic: author-email
Dynamic: classifier
Dynamic: description
Dynamic: description-content-type
Dynamic: home-page
Dynamic: keywords
Dynamic: license
Dynamic: license-file
Dynamic: platform
Dynamic: requires-dist
Dynamic: summary
